arxiv/submission/__init__.py
arxiv/submission/auth.py
arxiv/submission/config.py
arxiv/submission/core.py
arxiv/submission/exceptions.py
arxiv/submission/schedule.py
arxiv/submission/serializer.py
arxiv/submission/domain/__init__.py
arxiv/submission/domain/agent.py
arxiv/submission/domain/annotation.py
arxiv/submission/domain/compilation.py
arxiv/submission/domain/flag.py
arxiv/submission/domain/meta.py
arxiv/submission/domain/preview.py
arxiv/submission/domain/process.py
arxiv/submission/domain/proposal.py
arxiv/submission/domain/submission.py
arxiv/submission/domain/uploads.py
arxiv/submission/domain/util.py
arxiv/submission/domain/event/__init__.py
arxiv/submission/domain/event/base.py
arxiv/submission/domain/event/flag.py
arxiv/submission/domain/event/process.py
arxiv/submission/domain/event/proposal.py
arxiv/submission/domain/event/request.py
arxiv/submission/domain/event/util.py
arxiv/submission/domain/event/validators.py
arxiv/submission/domain/event/tests/__init__.py
arxiv/submission/domain/event/tests/test_abstract_cleanup.py
arxiv/submission/domain/event/tests/test_event_construction.py
arxiv/submission/domain/event/tests/test_hooks.py
arxiv/submission/domain/event/versioning/__init__.py
arxiv/submission/domain/event/versioning/_base.py
arxiv/submission/domain/event/versioning/version_0_0_0_example.py
arxiv/submission/domain/event/versioning/tests/__init__.py
arxiv/submission/domain/event/versioning/tests/test_example.py
arxiv/submission/domain/event/versioning/tests/test_versioning.py
arxiv/submission/domain/tests/__init__.py
arxiv/submission/domain/tests/test_events.py
arxiv/submission/process/__init__.py
arxiv/submission/process/process_source.py
arxiv/submission/process/tests.py
arxiv/submission/services/__init__.py
arxiv/submission/services/util.py
arxiv/submission/services/classic/__init__.py
arxiv/submission/services/classic/bootstrap.py
arxiv/submission/services/classic/event.py
arxiv/submission/services/classic/exceptions.py
arxiv_submission_core-0.7.2rc36.dist-info/LICENSE
arxiv_submission_core-0.7.2rc36.dist-info/METADATA
arxiv_submission_core-0.7.2rc36.dist-info/WHEEL
arxiv_submission_core-0.7.2rc36.dist-info/top_level.txt
arxiv_submission_core-0.7.2rc36.dist-info/RECORD
