Metadata-Version: 2.1
Name: arxiv-submission-core
Version: 0.7.2rc36
Summary: UNKNOWN
Home-page: UNKNOWN
Author: UNKNOWN
Author-email: UNKNOWN
License: UNKNOWN
Platform: UNKNOWN
Requires-Dist: arxiv-base (>=0.16.6)
Requires-Dist: arxiv-auth (>=0.4.2rc1)
Requires-Dist: flask
Requires-Dist: mysqlclient
Requires-Dist: bleach
Requires-Dist: unidecode
Requires-Dist: python-dateutil
Requires-Dist: sqlalchemy
Requires-Dist: flask-sqlalchemy
Requires-Dist: dataclasses
Requires-Dist: celery (==4.1.0)
Requires-Dist: kombu (==4.1.0)
Requires-Dist: redis (==2.10.6)
Requires-Dist: mypy-extensions (==0.4.1)
Requires-Dist: requests (==2.21.0)
Requires-Dist: semver (==2.8.1)
Requires-Dist: retry (==0.9.2)
Requires-Dist: pytz (==2018.7)
Requires-Dist: backports-datetime-fromisoformat (==1.0.0)
Requires-Dist: typing-extensions
